togo.cpython-314t-x86_64-linux-gnu.so
togo-0.3.3.dist-info/METADATA
togo-0.3.3.dist-info/WHEEL
togo-0.3.3.dist-info/top_level.txt
togo-0.3.3.dist-info/RECORD
togo-0.3.3.dist-info/licenses/LICENSE
