Metadata-Version: 2.1
Name: togo
Version: 0.3.3
Summary: Lightweight Python bindings for the TG geometry library
Author-email: Giorgio Salluzzo <giorgio.salluzzo@gmail.com>
License: MIT
Project-URL: Homepage, https://github.com/mindflayer/togo
Project-URL: Source, https://github.com/mindflayer/togo
Project-URL: Tracker, https://github.com/mindflayer/togo/issues
Classifier: Programming Language :: Python :: 3
Classifier: Programming Language :: C
Classifier: Operating System :: POSIX :: Linux
Classifier: Intended Audience :: Developers
Classifier: Topic :: Scientific/Engineering :: GIS
Requires-Python: >=3.8
License-File: LICENSE
